LICENSE.txt
MANIFEST.in
README.md
pyproject.toml
setup.cfg
setup.py
LeetTool/__init__.py
LeetTool/build.py
LeetTool/obj.py
LeetTool.egg-info/PKG-INFO
LeetTool.egg-info/SOURCES.txt
LeetTool.egg-info/dependency_links.txt
LeetTool.egg-info/top_level.txt