Metadata-Version: 2.1
Name: LeetTool
Version: 0.3
Summary: Selenium for Researcher
Home-page: https://github.com/ChangxingJiang/LeetCode-Toolkit-Py
Author: ChangXing
Author-email: 1278729001@qq.com
License: UNKNOWN
Keywords: LeetCode
Platform: UNKNOWN
Classifier: Development Status :: 3 - Alpha
Classifier: License :: OSI Approved :: MIT License
Classifier: Programming Language :: Python :: 3.8
Classifier: Programming Language :: Python
